malay/__init__.py
malay-0.0.1.dist-info/LICENSE
malay-0.0.1.dist-info/METADATA
malay-0.0.1.dist-info/WHEEL
malay-0.0.1.dist-info/top_level.txt
malay-0.0.1.dist-info/RECORD
