Metadata-Version: 2.1
Name: malay
Version: 0.0.1
Summary: A small utility for malay Language
Author-email: setools <setools.xyz@gmail.com>
Classifier: Programming Language :: Python :: 3
Classifier: License :: OSI Approved :: MIT License
Classifier: Operating System :: OS Independent
Requires-Python: >=3.7
License-File: LICENSE
